codedict/__init__.py
codedict/__version__.py
codedict/slices/slice.aa
CodeDict-0.0.5.dist-info/METADATA
CodeDict-0.0.5.dist-info/WHEEL
CodeDict-0.0.5.dist-info/top_level.txt
CodeDict-0.0.5.dist-info/RECORD
